callbotics_sdk/__init__.py
callbotics_sdk/client.py
callbotics_sdk/exceptions.py
callbotics_sdk/http.py
callbotics_sdk/models.py
callbotics_sdk/resources/__init__.py
callbotics_sdk/resources/actions.py
callbotics_sdk/resources/agents.py
callbotics_sdk/resources/analytics.py
callbotics_sdk/resources/base.py
callbotics_sdk/resources/billing.py
callbotics_sdk/resources/call_logs.py
callbotics_sdk/resources/calls.py
callbotics_sdk/resources/campaigns.py
callbotics_sdk/resources/contacts.py
callbotics_sdk/resources/live_monitoring.py
callbotics_sdk/resources/llm_configs.py
callbotics_sdk/resources/organisations.py
callbotics_sdk/resources/prompts.py
callbotics_sdk/resources/roles.py
callbotics_sdk/resources/stt_configs.py
callbotics_sdk/resources/telephony.py
callbotics_sdk/resources/users.py
callbotics_sdk/resources/voice_configs.py
callbotics_sdk/resources/workflows.py
callbotics_sdk-1.1.0.dist-info/METADATA
callbotics_sdk-1.1.0.dist-info/WHEEL
callbotics_sdk-1.1.0.dist-info/top_level.txt
callbotics_sdk-1.1.0.dist-info/RECORD
