Metadata-Version: 2.4
Name: callbotics-sdk
Version: 1.1.0
Summary: Python SDK for the Callbotics Core API
Home-page: https://github.com/callbotics/callbotics-sdk
Author: Callbotics
Author-email: support@callbotics.com
Keywords: callbotics,api,sdk,telephony,voice,ai,automation
Classifier: Development Status :: 4 - Beta
Classifier: Intended Audience :: Developers
Classifier: License :: OSI Approved :: MIT License
Classifier: Operating System :: OS Independent
Classifier: Programming Language :: Python :: 3
Classifier: Programming Language :: Python :: 3.9
Classifier: Programming Language :: Python :: 3.10
Classifier: Programming Language :: Python :: 3.11
Classifier: Programming Language :: Python :: 3.12
Classifier: Topic :: Communications :: Telephony
Classifier: Topic :: Software Development :: Libraries :: Python Modules
Requires-Python: >=3.9
Requires-Dist: httpx>=0.24.0
Provides-Extra: websocket
Requires-Dist: websockets>=11.0; extra == "websocket"
Provides-Extra: dev
Requires-Dist: pytest>=7.0; extra == "dev"
Requires-Dist: pytest-asyncio>=0.21; extra == "dev"
Requires-Dist: pytest-cov>=4.0; extra == "dev"
Dynamic: author
Dynamic: author-email
Dynamic: classifier
Dynamic: description
Dynamic: description-content-type
Dynamic: home-page
Dynamic: keywords
Dynamic: provides-extra
Dynamic: requires-dist
Dynamic: requires-python
Dynamic: summary
